{
  "aortic_root": {
    "tri_count": 84182,
    "non_manifold_edges": 1,
    "watertight": true,
    "aspect_ratio_p95": 2.755879502743175,
    "mesh_kind": "tube_segment",
    "boundary_loop_count": 0,
    "boundary_loops_all_closed": true,
    "passes_gate": false,
    "failure_reasons": [
      "non_manifold_edges_detected"
    ]
  },
  "ascending_aorta": {
    "tri_count": 85732,
    "non_manifold_edges": 0,
    "watertight": true,
    "aspect_ratio_p95": 2.3516983691057747,
    "mesh_kind": "tube_segment",
    "boundary_loop_count": 0,
    "boundary_loops_all_closed": true,
    "passes_gate": true,
    "failure_reasons": []
  },
  "leaflets": {
    "tri_count": 72,
    "non_manifold_edges": 0,
    "watertight": false,
    "aspect_ratio_p95": 21.6265055711178,
    "mesh_kind": "solid",
    "boundary_loop_count": null,
    "boundary_loops_all_closed": null,
    "passes_gate": false,
    "failure_reasons": [
      "tri_count_below_60000",
      "aspect_ratio_p95_exceeds_8.0",
      "mesh_not_watertight"
    ]
  },
  "annulus_ring": {
    "tri_count": 0,
    "non_manifold_edges": null,
    "watertight": null,
    "aspect_ratio_p95": null,
    "mesh_kind": "solid",
    "boundary_loop_count": null,
    "boundary_loops_all_closed": null,
    "passes_gate": false,
    "failure_reasons": [
      "mesh_file_missing:annulus_ring.stl"
    ]
  }
}
